pytest_colordots
