Metadata-Version: 1.1
Name: pytest-colordots
Version: 1.1
Summary: Colorizes the progress indicators
Home-page: https://github.com/svenstaro/pytest-colordots
Author: Sven-Hendrik Haase
Author-email: svenstaro@gmail.com
License: MIT
Platform: UNKNOWN
Classifier: Development Status :: 5 - Production/Stable
Classifier: Topic :: Software Development :: Testing
Classifier: Intended Audience :: Developers
Classifier: Operating System :: OS Independent
